[{
  "_id": {
    "$oid": "5f0000000000000000000001"
  },
  "address": "YourValidatorAddress1",
  "owner": {
    "$oid": "5f0000000000000000000011"
  },
  "stake": {
    "$oid": "5f0000000000000000000021"
  },
  "active": true,
  "__v": 0
},
{
  "_id": {
    "$oid": "5f0000000000000000000002"
  },
  "address": "YourValidatorAddress2",
  "owner": {
    "$oid": "5f0000000000000000000012"
  },
  "stake": {
    "$oid": "5f0000000000000000000022"
  },
  "active": true,
  "__v": 0
},
{
  "_id": {
    "$oid": "5f0000000000000000000003"
  },
  "address": "YourValidatorAddress3",
  "owner": {
    "$oid": "5f0000000000000000000013"
  },
  "stake": {
    "$oid": "5f0000000000000000000023"
  },
  "active": true,
  "__v": 0
},
{
  "_id": {
    "$oid": "5f0000000000000000000004"
  },
  "address": "YourValidatorAddress4",
  "owner": {
    "$oid": "5f0000000000000000000014"
  },
  "stake": {
    "$oid": "5f0000000000000000000024"
  },
  "active": true,
  "__v": 0
},
{
  "_id": {
    "$oid": "5f0000000000000000000005"
  },
  "address": "YourValidatorAddress5",
  "owner": {
    "$oid": "5f0000000000000000000015"
  },
  "stake": {
    "$oid": "5f0000000000000000000025"
  },
  "active": true,
  "__v": 0
},
{
  "_id": {
    "$oid": "5f0000000000000000000006"
  },
  "address": "YourValidatorAddress6",
  "owner": {
    "$oid": "5f0000000000000000000016"
  },
  "stake": {
    "$oid": "5f0000000000000000000026"
  },
  "active": true,
  "__v": 0
},
{
  "_id": {
    "$oid": "5f0000000000000000000007"
  },
  "address": "YourValidatorAddress7",
  "owner": {
    "$oid": "5f0000000000000000000017"
  },
  "stake": {
    "$oid": "5f0000000000000000000027"
  },
  "active": true,
  "__v": 0
},
{
  "_id": {
    "$oid": "5f0000000000000000000008"
  },
  "address": "YourValidatorAddress8",
  "owner": {
    "$oid": "5f0000000000000000000018"
  },
  "stake": {
    "$oid": "5f0000000000000000000028"
  },
  "active": true,
  "__v": 0
},
{
  "_id": {
    "$oid": "5f0000000000000000000009"
  },
  "address": "YourValidatorAddress9",
  "owner": {
    "$oid": "5f0000000000000000000019"
  },
  "stake": {
    "$oid": "5f0000000000000000000029"
  },
  "active": true,
  "__v": 0
}]